clusterscope/__init__.py
clusterscope/cache.py
clusterscope/cli.py
clusterscope/cluster_info.py
clusterscope/job_info.py
clusterscope/lib.py
clusterscope/parser.py
clusterscope/py.typed
clusterscope/shell.py
clusterscope/validate.py
clusterscope/slurm/parser.py
clusterscope/slurm/partition.py
clusterscope-0.0.29.dist-info/licenses/LICENSE
clusterscope-0.0.29.dist-info/METADATA
clusterscope-0.0.29.dist-info/WHEEL
clusterscope-0.0.29.dist-info/entry_points.txt
clusterscope-0.0.29.dist-info/top_level.txt
clusterscope-0.0.29.dist-info/RECORD
