Metadata-Version: 2.4
Name: clusterscope
Version: 0.0.29
Summary: Clusterscope is a CLI and python library to extract information from HPC Clusters and Jobs.
Author-email: Lucca Bertoncini <luccab@meta.com>, Kalyan Saladi <skalyan@meta.com>
License: MIT License
Project-URL: Homepage, https://github.com/facebookresearch/clusterscope
Project-URL: Issues, https://github.com/facebookresearch/clusterscope/issues
Requires-Python: >=3.10
License-File: LICENSE
Requires-Dist: click!=8.3.0,>=8.0.0
Requires-Dist: click-option-group
Provides-Extra: dev
Requires-Dist: flake8; extra == "dev"
Requires-Dist: black; extra == "dev"
Requires-Dist: ufmt; extra == "dev"
Requires-Dist: usort; extra == "dev"
Requires-Dist: mypy; extra == "dev"
Requires-Dist: pre-commit; extra == "dev"
Requires-Dist: build; extra == "dev"
Requires-Dist: types-click; extra == "dev"
Dynamic: license-file
